sqlitemgr/__init__.py
sqlitemgr/sqlitemgr.py
sqlitemgr-1.2.6.dist-info/DESCRIPTION.rst
sqlitemgr-1.2.6.dist-info/METADATA
sqlitemgr-1.2.6.dist-info/RECORD
sqlitemgr-1.2.6.dist-info/WHEEL
sqlitemgr-1.2.6.dist-info/entry_points.txt
sqlitemgr-1.2.6.dist-info/metadata.json
sqlitemgr-1.2.6.dist-info/top_level.txt
