Metadata-Version: 2.0
Name: sqlitemgr
Version: 1.2.6
Summary: A wrapper class for basic setup and management of an SQLite database.
Home-page: https://github.com/aescwork/sqlitemgr
Author: aescwork
Author-email: aescwork@protonmail.com
License: MIT
Keywords: sqlitemgr sqlite development database sqlite3
Platform: UNKNOWN
Classifier: Development Status :: 5 - Production/Stable
Classifier: Intended Audience :: Developers
Classifier: Topic :: Database
Classifier: Topic :: Software Development :: Libraries :: Python Modules
Classifier: License :: OSI Approved :: MIT License
Classifier: Programming Language :: Python :: 2.7
Classifier: Programming Language :: Python :: 3.5
Provides-Extra: dev
Requires-Dist: check-manifest; extra == 'dev'
Provides-Extra: test
Requires-Dist: coverage; extra == 'test'
